Workbook
Name country: 'Configuraciones'!$B$4
Name currency: 'Configuraciones'!$B$5
Name default_month: 'Configuraciones'!$B$6
Name tax_twilio: 'Configuraciones'!$B$9
Name tax_meta: 'Configuraciones'!$B$10
Name twilio_out: 'Configuraciones'!$B$13
Name twilio_in: 'Configuraciones'!$B$14
Name twilio_fail: 'Configuraciones'!$B$15
Name meta_marketing: 'Configuraciones'!$B$19
Name meta_utility: 'Configuraciones'!$B$20
Name meta_auth: 'Configuraciones'!$B$21
Name meta_service: 'Configuraciones'!$B$22
Name eng_enabled: 'Configuraciones'!$B$25
Name eng_fee: 'Configuraciones'!$B$26
Name eng_free: 'Configuraciones'!$B$27

Sheet Configuraciones
A1: Simulador de Campañas WhatsApp — Chile (compacto)
A3: General
A4: País | B4: Chile
A5: Moneda | B5: USD
A6: Mes por defecto (YYYY-MM) | B6: 2026-01
A8: Impuestos (IVA / impuesto sobre cargos)
A9: IVA sobre cargos Twilio | B9: 0.19 | D9: Nota | E9: Meta cobra solo cuando el mensaje se ENTREGA.
A10: IVA sobre cargos Meta (pass-through) | B10: 0.19 | D10: Nota | E10: Twilio cobra una tarifa fija por mensaje (in/out).
A12: Tarifas Twilio (USD)
A13: Tarifa por mensaje saliente (Outbound) | B13: 0.005
A14: Tarifa por mensaje entrante (Inbound) | B14: 0.005
A15: Tarifa por procesamiento fallido (opcional) | B15: 0.001
A17: Tarifas Meta por mensaje ENTREGADO — Chile (USD)
A18: Categoría | B18: Tarifa (USD)
A19: Marketing | B19: 0.1022
A20: Utility | B20: 0.023
A21: Authentication | B21: 0.023
A22: Service | B22: 0
A24: Engagement Suite (opcional)
A25: Habilitado? (Yes/No) | B25: No
A26: Tarifa por mensaje cuando aplica (USD) | B26: 0.015
A27: Franquicia gratis por mes (mensajes) | B27: 1000
A29: Fuentes (referencia)
A30: WhatsApp Platform Pricing (per-message, cobra al entregar) | B30: https://business.whatsapp.com/products/platform-pricing?lang=es_LA
A31: Twilio WhatsApp pricing (fee $0.005 in/out) | B31: https://www.twilio.com/en-us/whatsapp/pricing
A32: Manychat rates (USD, effective Jan 1 2026; incluye Chile) | B32: https://help.manychat.com/hc/en-us/articles/14281380243740-WhatsApp-pricing-guide
A33: Salesforce rate card (Service=0; Utility/Auth iguales para Chile) | B33: https://www.salesforce.com/en-us/wp-content/uploads/sites/4/assets/pdf/whatsapp-business-messaging-rate-card-mm-lite-dec-1-2025-to-jan-31-2026.pdf

Sheet Simulacion
A1: Simulación de campañas (edita SOLO celdas azules)
B3: Resumen
B4: Costo total (con IVA) | C4: =SUM(AB13:AB32) | E4: Mes | F4: ='Configuraciones'!$B$6
B5: Mensajes entregados (outbound) | C5: =SUM(G13:G32)
B6: Respondieron | C6: =SUM(K13:K32)
B7: Conversiones | C7: =SUM(AD13:AD32)
B8: Ingresos | C8: =SUM(AF13:AF32)
B9: ROI | C9: =IF(C4=0,"",(C8-C4)/C4)
A12: ID | B12: Campaña | C12: Mes | D12: Out Category | E12: Out Sent | F12: Fail Rate | G12: Out Delivered | H12: Meta Out $ | I12: Twilio Out $ | J12: Respond Rate | K12: Responders | L12: In msgs / resp | M12: Inbound msgs | N12: Reply tmpl / resp | O12: Reply Category | P12: Reply Sent | Q12: Reply Delivered | R12: Meta Reply $ | S12: Twilio In $ | T12: Twilio Reply $ | U12: Engage % | V12: Engage msgs | W12: Engage $ (alloc) | X12: Meta subtotal $ | Y12: Twilio subtotal $ | Z12: IVA Meta $ | AA12: IVA Twilio $ | AB12: Total con IVA | AC12: Conv Rate | AD12: Conversions | AE12: Rev/Conv | AF12: Revenue | AG12: Profit | AH12: ROI
A13: 1 | B13: Campaña ejemplo (500) | C13: ='Configuraciones'!$B$6 | D13: Marketing | E13: 500 | F13: 0 | G13: =ROUND(E13*(1-F13),0) | H13: =G13*IF(D13="Marketing",'Configuraciones'!$B$19,IF(D13="Utility",'Configuraciones'!$B$20,IF(D13="Authentication",'Configuraciones'!$B$21,'Configuraciones'!$B$22))) | I13: =E13*'Configuraciones'!$B$13 + (E13-G13)*'Configuraciones'!$B$15 | J13: 0.2 | K13: =ROUND(G13*J13,0) | L13: 1 | M13: =ROUND(K13*L13,0) | N13: 1 | O13: Utility | P13: =ROUND(K13*N13,0) | Q13: =ROUND(P13*(1-F13),0) | R13: =Q13*IF(O13="Marketing",'Configuraciones'!$B$19,IF(O13="Utility",'Configuraciones'!$B$20,IF(O13="Authentication",'Configuraciones'!$B$21,'Configuraciones'!$B$22))) | S13: =M13*'Configuraciones'!$B$14 | T13: =P13*'Configuraciones'!$B$13 + (P13-Q13)*'Configuraciones'!$B$15 | U13: 0 | V13: =ROUND((E13+M13+P13)*U13,0) | W13: =IF($C$39=0,0,IF($C$36=0,0,$C$39*V13/$C$36)) | X13: =H13+R13 | Y13: =I13+S13+T13 | Z13: =X13*'Configuraciones'!$B$10 | AA13: =Y13*'Configuraciones'!$B$9 | AB13: =X13+Y13+Z13+AA13+W13 | AC13: 0.05 | AD13: =ROUND(K13*AC13,0) | AE13: 50 | AF13: =AD13*AE13 | AG13: =AF13-AB13 | AH13: =IF(AB13=0,"",AG13/AB13)
A14: 2 | B14: Campaña ejemplo (3000) | C14: ='Configuraciones'!$B$6 | D14: Marketing | E14: 3000 | F14: 0 | G14: =ROUND(E14*(1-F14),0) | H14: =G14*IF(D14="Marketing",'Configuraciones'!$B$19,IF(D14="Utility",'Configuraciones'!$B$20,IF(D14="Authentication",'Configuraciones'!$B$21,'Configuraciones'!$B$22))) | I14: =E14*'Configuraciones'!$B$13 + (E14-G14)*'Configuraciones'!$B$15 | J14: 0.15 | K14: =ROUND(G14*J14,0) | L14: 1 | M14: =ROUND(K14*L14,0) | N14: 1 | O14: Utility | P14: =ROUND(K14*N14,0) | Q14: =ROUND(P14*(1-F14),0) | R14: =Q14*IF(O14="Marketing",'Configuraciones'!$B$19,IF(O14="Utility",'Configuraciones'!$B$20,IF(O14="Authentication",'Configuraciones'!$B$21,'Configuraciones'!$B$22))) | S14: =M14*'Configuraciones'!$B$14 | T14: =P14*'Configuraciones'!$B$13 + (P14-Q14)*'Configuraciones'!$B$15 | U14: 0 | V14: =ROUND((E14+M14+P14)*U14,0) | W14: =IF($C$39=0,0,IF($C$36=0,0,$C$39*V14/$C$36)) | X14: =H14+R14 | Y14: =I14+S14+T14 | Z14: =X14*'Configuraciones'!$B$10 | AA14: =Y14*'Configuraciones'!$B$9 | AB14: =X14+Y14+Z14+AA14+W14 | AC14: 0.04 | AD14: =ROUND(K14*AC14,0) | AE14: 50 | AF14: =AD14*AE14 | AG14: =AF14-AB14 | AH14: =IF(AB14=0,"",AG14/AB14)
A15: 3 | B15: Campaña 3 | C15: ='Configuraciones'!$B$6 | D15: Marketing | E15: 0 | F15: 0 | G15: =ROUND(E15*(1-F15),0) | H15: =G15*IF(D15="Marketing",'Configuraciones'!$B$19,IF(D15="Utility",'Configuraciones'!$B$20,IF(D15="Authentication",'Configuraciones'!$B$21,'Configuraciones'!$B$22))) | I15: =E15*'Configuraciones'!$B$13 + (E15-G15)*'Configuraciones'!$B$15 | J15: 0.2 | K15: =ROUND(G15*J15,0) | L15: 1 | M15: =ROUND(K15*L15,0) | N15: 1 | O15: Utility | P15: =ROUND(K15*N15,0) | Q15: =ROUND(P15*(1-F15),0) | R15: =Q15*IF(O15="Marketing",'Configuraciones'!$B$19,IF(O15="Utility",'Configuraciones'!$B$20,IF(O15="Authentication",'Configuraciones'!$B$21,'Configuraciones'!$B$22))) | S15: =M15*'Configuraciones'!$B$14 | T15: =P15*'Configuraciones'!$B$13 + (P15-Q15)*'Configuraciones'!$B$15 | U15: 0 | V15: =ROUND((E15+M15+P15)*U15,0) | W15: =IF($C$39=0,0,IF($C$36=0,0,$C$39*V15/$C$36)) | X15: =H15+R15 | Y15: =I15+S15+T15 | Z15: =X15*'Configuraciones'!$B$10 | AA15: =Y15*'Configuraciones'!$B$9 | AB15: =X15+Y15+Z15+AA15+W15 | AC15: 0.05 | AD15: =ROUND(K15*AC15,0) | AE15: 50 | AF15: =AD15*AE15 | AG15: =AF15-AB15 | AH15: =IF(AB15=0,"",AG15/AB15)
A16: 4 | B16: Campaña 4 | C16: ='Configuraciones'!$B$6 | D16: Marketing | E16: 0 | F16: 0 | G16: =ROUND(E16*(1-F16),0) | H16: =G16*IF(D16="Marketing",'Configuraciones'!$B$19,IF(D16="Utility",'Configuraciones'!$B$20,IF(D16="Authentication",'Configuraciones'!$B$21,'Configuraciones'!$B$22))) | I16: =E16*'Configuraciones'!$B$13 + (E16-G16)*'Configuraciones'!$B$15 | J16: 0.2 | K16: =ROUND(G16*J16,0) | L16: 1 | M16: =ROUND(K16*L16,0) | N16: 1 | O16: Utility | P16: =ROUND(K16*N16,0) | Q16: =ROUND(P16*(1-F16),0) | R16: =Q16*IF(O16="Marketing",'Configuraciones'!$B$19,IF(O16="Utility",'Configuraciones'!$B$20,IF(O16="Authentication",'Configuraciones'!$B$21,'Configuraciones'!$B$22))) | S16: =M16*'Configuraciones'!$B$14 | T16: =P16*'Configuraciones'!$B$13 + (P16-Q16)*'Configuraciones'!$B$15 | U16: 0 | V16: =ROUND((E16+M16+P16)*U16,0) | W16: =IF($C$39=0,0,IF($C$36=0,0,$C$39*V16/$C$36)) | X16: =H16+R16 | Y16: =I16+S16+T16 | Z16: =X16*'Configuraciones'!$B$10 | AA16: =Y16*'Configuraciones'!$B$9 | AB16: =X16+Y16+Z16+AA16+W16 | AC16: 0.05 | AD16: =ROUND(K16*AC16,0) | AE16: 50 | AF16: =AD16*AE16 | AG16: =AF16-AB16 | AH16: =IF(AB16=0,"",AG16/AB16)
A17: 5 | B17: Campaña 5 | C17: ='Configuraciones'!$B$6 | D17: Marketing | E17: 0 | F17: 0 | G17: =ROUND(E17*(1-F17),0) | H17: =G17*IF(D17="Marketing",'Configuraciones'!$B$19,IF(D17="Utility",'Configuraciones'!$B$20,IF(D17="Authentication",'Configuraciones'!$B$21,'Configuraciones'!$B$22))) | I17: =E17*'Configuraciones'!$B$13 + (E17-G17)*'Configuraciones'!$B$15 | J17: 0.2 | K17: =ROUND(G17*J17,0) | L17: 1 | M17: =ROUND(K17*L17,0) | N17: 1 | O17: Utility | P17: =ROUND(K17*N17,0) | Q17: =ROUND(P17*(1-F17),0) | R17: =Q17*IF(O17="Marketing",'Configuraciones'!$B$19,IF(O17="Utility",'Configuraciones'!$B$20,IF(O17="Authentication",'Configuraciones'!$B$21,'Configuraciones'!$B$22))) | S17: =M17*'Configuraciones'!$B$14 | T17: =P17*'Configuraciones'!$B$13 + (P17-Q17)*'Configuraciones'!$B$15 | U17: 0 | V17: =ROUND((E17+M17+P17)*U17,0) | W17: =IF($C$39=0,0,IF($C$36=0,0,$C$39*V17/$C$36)) | X17: =H17+R17 | Y17: =I17+S17+T17 | Z17: =X17*'Configuraciones'!$B$10 | AA17: =Y17*'Configuraciones'!$B$9 | AB17: =X17+Y17+Z17+AA17+W17 | AC17: 0.05 | AD17: =ROUND(K17*AC17,0) | AE17: 50 | AF17: =AD17*AE17 | AG17: =AF17-AB17 | AH17: =IF(AB17=0,"",AG17/AB17)
A18: 6 | B18: Campaña 6 | C18: ='Configuraciones'!$B$6 | D18: Marketing | E18: 0 | F18: 0 | G18: =ROUND(E18*(1-F18),0) | H18: =G18*IF(D18="Marketing",'Configuraciones'!$B$19,IF(D18="Utility",'Configuraciones'!$B$20,IF(D18="Authentication",'Configuraciones'!$B$21,'Configuraciones'!$B$22))) | I18: =E18*'Configuraciones'!$B$13 + (E18-G18)*'Configuraciones'!$B$15 | J18: 0.2 | K18: =ROUND(G18*J18,0) | L18: 1 | M18: =ROUND(K18*L18,0) | N18: 1 | O18: Utility | P18: =ROUND(K18*N18,0) | Q18: =ROUND(P18*(1-F18),0) | R18: =Q18*IF(O18="Marketing",'Configuraciones'!$B$19,IF(O18="Utility",'Configuraciones'!$B$20,IF(O18="Authentication",'Configuraciones'!$B$21,'Configuraciones'!$B$22))) | S18: =M18*'Configuraciones'!$B$14 | T18: =P18*'Configuraciones'!$B$13 + (P18-Q18)*'Configuraciones'!$B$15 | U18: 0 | V18: =ROUND((E18+M18+P18)*U18,0) | W18: =IF($C$39=0,0,IF($C$36=0,0,$C$39*V18/$C$36)) | X18: =H18+R18 | Y18: =I18+S18+T18 | Z18: =X18*'Configuraciones'!$B$10 | AA18: =Y18*'Configuraciones'!$B$9 | AB18: =X18+Y18+Z18+AA18+W18 | AC18: 0.05 | AD18: =ROUND(K18*AC18,0) | AE18: 50 | AF18: =AD18*AE18 | AG18: =AF18-AB18 | AH18: =IF(AB18=0,"",AG18/AB18)
A19: 7 | B19: Campaña 7 | C19: ='Configuraciones'!$B$6 | D19: Marketing | E19: 0 | F19: 0 | G19: =ROUND(E19*(1-F19),0) | H19: =G19*IF(D19="Marketing",'Configuraciones'!$B$19,IF(D19="Utility",'Configuraciones'!$B$20,IF(D19="Authentication",'Configuraciones'!$B$21,'Configuraciones'!$B$22))) | I19: =E19*'Configuraciones'!$B$13 + (E19-G19)*'Configuraciones'!$B$15 | J19: 0.2 | K19: =ROUND(G19*J19,0) | L19: 1 | M19: =ROUND(K19*L19,0) | N19: 1 | O19: Utility | P19: =ROUND(K19*N19,0) | Q19: =ROUND(P19*(1-F19),0) | R19: =Q19*IF(O19="Marketing",'Configuraciones'!$B$19,IF(O19="Utility",'Configuraciones'!$B$20,IF(O19="Authentication",'Configuraciones'!$B$21,'Configuraciones'!$B$22))) | S19: =M19*'Configuraciones'!$B$14 | T19: =P19*'Configuraciones'!$B$13 + (P19-Q19)*'Configuraciones'!$B$15 | U19: 0 | V19: =ROUND((E19+M19+P19)*U19,0) | W19: =IF($C$39=0,0,IF($C$36=0,0,$C$39*V19/$C$36)) | X19: =H19+R19 | Y19: =I19+S19+T19 | Z19: =X19*'Configuraciones'!$B$10 | AA19: =Y19*'Configuraciones'!$B$9 | AB19: =X19+Y19+Z19+AA19+W19 | AC19: 0.05 | AD19: =ROUND(K19*AC19,0) | AE19: 50 | AF19: =AD19*AE19 | AG19: =AF19-AB19 | AH19: =IF(AB19=0,"",AG19/AB19)
A20: 8 | B20: Campaña 8 | C20: ='Configuraciones'!$B$6 | D20: Marketing | E20: 0 | F20: 0 | G20: =ROUND(E20*(1-F20),0) | H20: =G20*IF(D20="Marketing",'Configuraciones'!$B$19,IF(D20="Utility",'Configuraciones'!$B$20,IF(D20="Authentication",'Configuraciones'!$B$21,'Configuraciones'!$B$22))) | I20: =E20*'Configuraciones'!$B$13 + (E20-G20)*'Configuraciones'!$B$15 | J20: 0.2 | K20: =ROUND(G20*J20,0) | L20: 1 | M20: =ROUND(K20*L20,0) | N20: 1 | O20: Utility | P20: =ROUND(K20*N20,0) | Q20: =ROUND(P20*(1-F20),0) | R20: =Q20*IF(O20="Marketing",'Configuraciones'!$B$19,IF(O20="Utility",'Configuraciones'!$B$20,IF(O20="Authentication",'Configuraciones'!$B$21,'Configuraciones'!$B$22))) | S20: =M20*'Configuraciones'!$B$14 | T20: =P20*'Configuraciones'!$B$13 + (P20-Q20)*'Configuraciones'!$B$15 | U20: 0 | V20: =ROUND((E20+M20+P20)*U20,0) | W20: =IF($C$39=0,0,IF($C$36=0,0,$C$39*V20/$C$36)) | X20: =H20+R20 | Y20: =I20+S20+T20 | Z20: =X20*'Configuraciones'!$B$10 | AA20: =Y20*'Configuraciones'!$B$9 | AB20: =X20+Y20+Z20+AA20+W20 | AC20: 0.05 | AD20: =ROUND(K20*AC20,0) | AE20: 50 | AF20: =AD20*AE20 | AG20: =AF20-AB20 | AH20: =IF(AB20=0,"",AG20/AB20)
A21: 9 | B21: Campaña 9 | C21: ='Configuraciones'!$B$6 | D21: Marketing | E21: 0 | F21: 0 | G21: =ROUND(E21*(1-F21),0) | H21: =G21*IF(D21="Marketing",'Configuraciones'!$B$19,IF(D21="Utility",'Configuraciones'!$B$20,IF(D21="Authentication",'Configuraciones'!$B$21,'Configuraciones'!$B$22))) | I21: =E21*'Configuraciones'!$B$13 + (E21-G21)*'Configuraciones'!$B$15 | J21: 0.2 | K21: =ROUND(G21*J21,0) | L21: 1 | M21: =ROUND(K21*L21,0) | N21: 1 | O21: Utility | P21: =ROUND(K21*N21,0) | Q21: =ROUND(P21*(1-F21),0) | R21: =Q21*IF(O21="Marketing",'Configuraciones'!$B$19,IF(O21="Utility",'Configuraciones'!$B$20,IF(O21="Authentication",'Configuraciones'!$B$21,'Configuraciones'!$B$22))) | S21: =M21*'Configuraciones'!$B$14 | T21: =P21*'Configuraciones'!$B$13 + (P21-Q21)*'Configuraciones'!$B$15 | U21: 0 | V21: =ROUND((E21+M21+P21)*U21,0) | W21: =IF($C$39=0,0,IF($C$36=0,0,$C$39*V21/$C$36)) | X21: =H21+R21 | Y21: =I21+S21+T21 | Z21: =X21*'Configuraciones'!$B$10 | AA21: =Y21*'Configuraciones'!$B$9 | AB21: =X21+Y21+Z21+AA21+W21 | AC21: 0.05 | AD21: =ROUND(K21*AC21,0) | AE21: 50 | AF21: =AD21*AE21 | AG21: =AF21-AB21 | AH21: =IF(AB21=0,"",AG21/AB21)
A22: 10 | B22: Campaña 10 | C22: ='Configuraciones'!$B$6 | D22: Marketing | E22: 0 | F22: 0 | G22: =ROUND(E22*(1-F22),0) | H22: =G22*IF(D22="Marketing",'Configuraciones'!$B$19,IF(D22="Utility",'Configuraciones'!$B$20,IF(D22="Authentication",'Configuraciones'!$B$21,'Configuraciones'!$B$22))) | I22: =E22*'Configuraciones'!$B$13 + (E22-G22)*'Configuraciones'!$B$15 | J22: 0.2 | K22: =ROUND(G22*J22,0) | L22: 1 | M22: =ROUND(K22*L22,0) | N22: 1 | O22: Utility | P22: =ROUND(K22*N22,0) | Q22: =ROUND(P22*(1-F22),0) | R22: =Q22*IF(O22="Marketing",'Configuraciones'!$B$19,IF(O22="Utility",'Configuraciones'!$B$20,IF(O22="Authentication",'Configuraciones'!$B$21,'Configuraciones'!$B$22))) | S22: =M22*'Configuraciones'!$B$14 | T22: =P22*'Configuraciones'!$B$13 + (P22-Q22)*'Configuraciones'!$B$15 | U22: 0 | V22: =ROUND((E22+M22+P22)*U22,0) | W22: =IF($C$39=0,0,IF($C$36=0,0,$C$39*V22/$C$36)) | X22: =H22+R22 | Y22: =I22+S22+T22 | Z22: =X22*'Configuraciones'!$B$10 | AA22: =Y22*'Configuraciones'!$B$9 | AB22: =X22+Y22+Z22+AA22+W22 | AC22: 0.05 | AD22: =ROUND(K22*AC22,0) | AE22: 50 | AF22: =AD22*AE22 | AG22: =AF22-AB22 | AH22: =IF(AB22=0,"",AG22/AB22)
A23: 11 | B23: Campaña 11 | C23: ='Configuraciones'!$B$6 | D23: Marketing | E23: 0 | F23: 0 | G23: =ROUND(E23*(1-F23),0) | H23: =G23*IF(D23="Marketing",'Configuraciones'!$B$19,IF(D23="Utility",'Configuraciones'!$B$20,IF(D23="Authentication",'Configuraciones'!$B$21,'Configuraciones'!$B$22))) | I23: =E23*'Configuraciones'!$B$13 + (E23-G23)*'Configuraciones'!$B$15 | J23: 0.2 | K23: =ROUND(G23*J23,0) | L23: 1 | M23: =ROUND(K23*L23,0) | N23: 1 | O23: Utility | P23: =ROUND(K23*N23,0) | Q23: =ROUND(P23*(1-F23),0) | R23: =Q23*IF(O23="Marketing",'Configuraciones'!$B$19,IF(O23="Utility",'Configuraciones'!$B$20,IF(O23="Authentication",'Configuraciones'!$B$21,'Configuraciones'!$B$22))) | S23: =M23*'Configuraciones'!$B$14 | T23: =P23*'Configuraciones'!$B$13 + (P23-Q23)*'Configuraciones'!$B$15 | U23: 0 | V23: =ROUND((E23+M23+P23)*U23,0) | W23: =IF($C$39=0,0,IF($C$36=0,0,$C$39*V23/$C$36)) | X23: =H23+R23 | Y23: =I23+S23+T23 | Z23: =X23*'Configuraciones'!$B$10 | AA23: =Y23*'Configuraciones'!$B$9 | AB23: =X23+Y23+Z23+AA23+W23 | AC23: 0.05 | AD23: =ROUND(K23*AC23,0) | AE23: 50 | AF23: =AD23*AE23 | AG23: =AF23-AB23 | AH23: =IF(AB23=0,"",AG23/AB23)
A24: 12 | B24: Campaña 12 | C24: ='Configuraciones'!$B$6 | D24: Marketing | E24: 0 | F24: 0 | G24: =ROUND(E24*(1-F24),0) | H24: =G24*IF(D24="Marketing",'Configuraciones'!$B$19,IF(D24="Utility",'Configuraciones'!$B$20,IF(D24="Authentication",'Configuraciones'!$B$21,'Configuraciones'!$B$22))) | I24: =E24*'Configuraciones'!$B$13 + (E24-G24)*'Configuraciones'!$B$15 | J24: 0.2 | K24: =ROUND(G24*J24,0) | L24: 1 | M24: =ROUND(K24*L24,0) | N24: 1 | O24: Utility | P24: =ROUND(K24*N24,0) | Q24: =ROUND(P24*(1-F24),0) | R24: =Q24*IF(O24="Marketing",'Configuraciones'!$B$19,IF(O24="Utility",'Configuraciones'!$B$20,IF(O24="Authentication",'Configuraciones'!$B$21,'Configuraciones'!$B$22))) | S24: =M24*'Configuraciones'!$B$14 | T24: =P24*'Configuraciones'!$B$13 + (P24-Q24)*'Configuraciones'!$B$15 | U24: 0 | V24: =ROUND((E24+M24+P24)*U24,0) | W24: =IF($C$39=0,0,IF($C$36=0,0,$C$39*V24/$C$36)) | X24: =H24+R24 | Y24: =I24+S24+T24 | Z24: =X24*'Configuraciones'!$B$10 | AA24: =Y24*'Configuraciones'!$B$9 | AB24: =X24+Y24+Z24+AA24+W24 | AC24: 0.05 | AD24: =ROUND(K24*AC24,0) | AE24: 50 | AF24: =AD24*AE24 | AG24: =AF24-AB24 | AH24: =IF(AB24=0,"",AG24/AB24)
... A32: 20 | B32: Campaña 20 | C32: ='Configuraciones'!$B$6 | D32: Marketing | E32: 0 | F32: 0 | G32: =ROUND(E32*(1-F32),0) | H32: =G32*IF(D32="Marketing",'Configuraciones'!$B$19,IF(D32="Utility",'Configuraciones'!$B$20,IF(D32="Authentication",'Configuraciones'!$B$21,'Configuraciones'!$B$22))) | I32: =E32*'Configuraciones'!$B$13 + (E32-G32)*'Configuraciones'!$B$15 | J32: 0.2 | K32: =ROUND(G32*J32,0) | L32: 1 | M32: =ROUND(K32*L32,0) | N32: 1 | O32: Utility | P32: =ROUND(K32*N32,0) | Q32: =ROUND(P32*(1-F32),0) | R32: =Q32*IF(O32="Marketing",'Configuraciones'!$B$19,IF(O32="Utility",'Configuraciones'!$B$20,IF(O32="Authentication",'Configuraciones'!$B$21,'Configuraciones'!$B$22))) | S32: =M32*'Configuraciones'!$B$14 | T32: =P32*'Configuraciones'!$B$13 + (P32-Q32)*'Configuraciones'!$B$15 | U32: 0 | V32: =ROUND((E32+M32+P32)*U32,0) | W32: =IF($C$39=0,0,IF($C$36=0,0,$C$39*V32/$C$36)) | X32: =H32+R32 | Y32: =I32+S32+T32 | Z32: =X32*'Configuraciones'!$B$10 | AA32: =Y32*'Configuraciones'!$B$9 | AB32: =X32+Y32+Z32+AA32+W32 | AC32: 0.05 | AD32: =ROUND(K32*AC32,0) | AE32: 50 | AF32: =AD32*AE32 | AG32: =AF32-AB32 | AH32: =IF(AB32=0,"",AG32/AB32)
B34: Engagement Suite (cálculo global)
B35: Habilitado? | C35: ='Configuraciones'!$B$25
B36: Total Engage msgs | C36: =SUM(V13:V32)
B37: Franquicia gratis | C37: ='Configuraciones'!$B$27
B38: Mensajes cobrados | C38: =MAX(0,C36-C37)
B39: Costo total Engage $ | C39: =IF(C35="Yes",C38*'Configuraciones'!$B$26,0)
