Workbook

Sheet Inputs & Settings
A1: WhatsApp Cost Model (Twilio + Meta) — Inputs
A2: Edit BLUE cells only. Black cells are formulas.
A4: General | D4: Meta rates (per message delivered)
A5: Country | B5: Chile | D5: Category | E5: Rate (USD)
A6: Currency | B6: USD | D6: Marketing | E6: 0.0889
A7: Month (YYYY-MM) default | B7: 2026-02 | D7: Utility | E7: 0
D8: Authentication | E8: 0
A9: Tax / Sales Tax | D9: Service | E9: 0
A10: Tax rate on Twilio charges | B10: 0.19
A11: Tax rate on Meta pass-through | B11: 0.19 | D11: Defaults
A12: Note | B12: If Twilio invoices everything together, tax may apply to both. Adjust as needed. | D12: Assume replies are Service? | E12: Yes
D13: Default reply template category (if used) | E13: Marketing
A14: Twilio per-message fees
A15: Channels Outbound per message (USD) | B15: 0.005 | D15: Manage
A16: Channels Inbound per message (USD) | B16: 0.005 | D16: Denpar | E16: 0.3
A17: Failed message processing fee (USD) — optional | B17: 0.001
A19: Engagement Suite (optional)
A20: Enabled? (Yes/No) | B20: No
A21: Fee per message when used (USD) | B21: 0.015
A22: Free allowance per month (messages) | B22: 1000

Sheet Campaign Planner
A1: Campaign ID | B1: Campaign Name | C1: Month (YYYY-MM) | D1: Outbound Category | E1: Planned Outbound Msgs | F1: Failure Rate | G1: Response Rate | H1: Avg Inbound Msgs / Responder | I1: Avg Reply Msgs / Responder | J1: Reply Template % | K1: Reply Template Category | L1: Engagement Used? | M1: Engagement Apply % | N1: Notes | O1: Delivered Outbound | P1: Failed Outbound | Q1: Responders | R1: Inbound Msgs | S1: Reply Msgs (Total) | T1: Reply Msgs (Template) | U1: Reply Msgs (Service) | V1: Meta Cost (Outbound) | W1: Meta Cost (Reply Templates) | X1: Twilio Cost (Outbound) | Y1: Twilio Cost (Inbound) | Z1: Twilio Cost (Reply Outbound) | AA1: Twilio Failed Fee | AB1: Engagement Msgs
A2: 1 | B2: campaña1 | C2: ='Inputs & Settings'!B7 -> 2026-02 | D2: Marketing | F2: 0.04 | G2: 0.12 | H2: 1 | I2: 1 | J2: 0 | K2: ='Inputs & Settings'!E13 -> Marketing | L2: ='Inputs & Settings'!B20 -> No | M2: 0 | O2: =ROUND(E2*(1-F2),0) -> 0 | P2: =E2-O2 -> 0 | Q2: =ROUND(O2*G2,0) -> 0 | R2: =ROUND(Q2*H2,0) -> 0 | S2: =ROUND(Q2*I2,0) -> 0 | T2: =ROUND(S2*J2,0) -> 0 | U2: =S2-T2 -> 0 | V2: =O2*IFERROR(VLOOKUP(D2,'Inputs & Settings'!D6:E9,2,FALSE),0) -> 0 | W2: =T2*IFERROR(VLOOKUP(K2,'Inputs & Settings'!D6:E9,2,FALSE),0) -> 0 | X2: =O2*'Inputs & Settings'!B15 -> 0 | Y2: =R2*'Inputs & Settings'!B16 -> 0 | Z2: =S2*'Inputs & Settings'!B15 -> 0 | AA2: =P2*'Inputs & Settings'!B17 -> 0 | AB2: =IF(L2="Yes",ROUND((O2+S2)*M2,0),0) -> 0
A3: 2 | B3: campaña2 | C3: ='Inputs & Settings'!B7 -> 2026-02 | D3: Marketing | E3: 3000 | F3: 0.05 | G3: 0.12 | H3: 1 | I3: 1 | J3: 0 | K3: ='Inputs & Settings'!E13 -> Marketing | L3: ='Inputs & Settings'!B20 -> No | M3: 0 | O3: =ROUND(E3*(1-F3),0) -> 2850 | P3: =E3-O3 -> 150 | Q3: =ROUND(O3*G3,0) -> 342 | R3: =ROUND(Q3*H3,0) -> 342 | S3: =ROUND(Q3*I3,0) -> 342 | T3: =ROUND(S3*J3,0) -> 0 | U3: =S3-T3 -> 342 | V3: =O3*IFERROR(VLOOKUP(D3,'Inputs & Settings'!D6:E9,2,FALSE),0) -> 253.365 | W3: =T3*IFERROR(VLOOKUP(K3,'Inputs & Settings'!D6:E9,2,FALSE),0) -> 0 | X3: =O3*'Inputs & Settings'!B15 -> 14.25 | Y3: =R3*'Inputs & Settings'!B16 -> 1.71 | Z3: =S3*'Inputs & Settings'!B15 -> 1.71 | AA3: =P3*'Inputs & Settings'!B17 -> 0.15 | AB3: =IF(L3="Yes",ROUND((O3+S3)*M3,0),0) -> 0
A4: 3 | C4: ='Inputs & Settings'!B7 -> 2026-02 | D4: Marketing | E4: 0 | F4: 0 | G4: 0 | H4: 1 | I4: 1 | J4: 0 | K4: ='Inputs & Settings'!E13 -> Marketing | L4: ='Inputs & Settings'!B20 -> No | M4: 0 | O4: =ROUND(E4*(1-F4),0) -> 0 | P4: =E4-O4 -> 0 | Q4: =ROUND(O4*G4,0) -> 0 | R4: =ROUND(Q4*H4,0) -> 0 | S4: =ROUND(Q4*I4,0) -> 0 | T4: =ROUND(S4*J4,0) -> 0 | U4: =S4-T4 -> 0 | V4: =O4*IFERROR(VLOOKUP(D4,'Inputs & Settings'!D6:E9,2,FALSE),0) -> 0 | W4: =T4*IFERROR(VLOOKUP(K4,'Inputs & Settings'!D6:E9,2,FALSE),0) -> 0 | X4: =O4*'Inputs & Settings'!B15 -> 0 | Y4: =R4*'Inputs & Settings'!B16 -> 0 | Z4: =S4*'Inputs & Settings'!B15 -> 0 | AA4: =P4*'Inputs & Settings'!B17 -> 0 | AB4: =IF(L4="Yes",ROUND((O4+S4)*M4,0),0) -> 0
A5: 4 | C5: ='Inputs & Settings'!B7 -> 2026-02 | D5: Marketing | E5: 0 | F5: 0 | G5: 0 | H5: 1 | I5: 1 | J5: 0 | K5: ='Inputs & Settings'!E13 -> Marketing | L5: ='Inputs & Settings'!B20 -> No | M5: 0 | O5: =ROUND(E5*(1-F5),0) -> 0 | P5: =E5-O5 -> 0 | Q5: =ROUND(O5*G5,0) -> 0 | R5: =ROUND(Q5*H5,0) -> 0 | S5: =ROUND(Q5*I5,0) -> 0 | T5: =ROUND(S5*J5,0) -> 0 | U5: =S5-T5 -> 0 | V5: =O5*IFERROR(VLOOKUP(D5,'Inputs & Settings'!D6:E9,2,FALSE),0) -> 0 | W5: =T5*IFERROR(VLOOKUP(K5,'Inputs & Settings'!D6:E9,2,FALSE),0) -> 0 | X5: =O5*'Inputs & Settings'!B15 -> 0 | Y5: =R5*'Inputs & Settings'!B16 -> 0 | Z5: =S5*'Inputs & Settings'!B15 -> 0 | AA5: =P5*'Inputs & Settings'!B17 -> 0 | AB5: =IF(L5="Yes",ROUND((O5+S5)*M5,0),0) -> 0
A6: 5 | C6: ='Inputs & Settings'!B7 -> 2026-02 | D6: Marketing | E6: 0 | F6: 0 | G6: 0 | H6: 1 | I6: 1 | J6: 0 | K6: ='Inputs & Settings'!E13 -> Marketing | L6: ='Inputs & Settings'!B20 -> No | M6: 0 | O6: =ROUND(E6*(1-F6),0) -> 0 | P6: =E6-O6 -> 0 | Q6: =ROUND(O6*G6,0) -> 0 | R6: =ROUND(Q6*H6,0) -> 0 | S6: =ROUND(Q6*I6,0) -> 0 | T6: =ROUND(S6*J6,0) -> 0 | U6: =S6-T6 -> 0 | V6: =O6*IFERROR(VLOOKUP(D6,'Inputs & Settings'!D6:E9,2,FALSE),0) -> 0 | W6: =T6*IFERROR(VLOOKUP(K6,'Inputs & Settings'!D6:E9,2,FALSE),0) -> 0 | X6: =O6*'Inputs & Settings'!B15 -> 0 | Y6: =R6*'Inputs & Settings'!B16 -> 0 | Z6: =S6*'Inputs & Settings'!B15 -> 0 | AA6: =P6*'Inputs & Settings'!B17 -> 0 | AB6: =IF(L6="Yes",ROUND((O6+S6)*M6,0),0) -> 0
A7: 6 | C7: ='Inputs & Settings'!B7 -> 2026-02 | D7: Marketing | E7: 0 | F7: 0 | G7: 0 | H7: 1 | I7: 1 | J7: 0 | K7: ='Inputs & Settings'!E13 -> Marketing | L7: ='Inputs & Settings'!B20 -> No | M7: 0 | O7: =ROUND(E7*(1-F7),0) -> 0 | P7: =E7-O7 -> 0 | Q7: =ROUND(O7*G7,0) -> 0 | R7: =ROUND(Q7*H7,0) -> 0 | S7: =ROUND(Q7*I7,0) -> 0 | T7: =ROUND(S7*J7,0) -> 0 | U7: =S7-T7 -> 0 | V7: =O7*IFERROR(VLOOKUP(D7,'Inputs & Settings'!D6:E9,2,FALSE),0) -> 0 | W7: =T7*IFERROR(VLOOKUP(K7,'Inputs & Settings'!D6:E9,2,FALSE),0) -> 0 | X7: =O7*'Inputs & Settings'!B15 -> 0 | Y7: =R7*'Inputs & Settings'!B16 -> 0 | Z7: =S7*'Inputs & Settings'!B15 -> 0 | AA7: =P7*'Inputs & Settings'!B17 -> 0 | AB7: =IF(L7="Yes",ROUND((O7+S7)*M7,0),0) -> 0
A8: 7 | C8: ='Inputs & Settings'!B7 -> 2026-02 | D8: Marketing | E8: 0 | F8: 0 | G8: 0 | H8: 1 | I8: 1 | J8: 0 | K8: ='Inputs & Settings'!E13 -> Marketing | L8: ='Inputs & Settings'!B20 -> No | M8: 0 | O8: =ROUND(E8*(1-F8),0) -> 0 | P8: =E8-O8 -> 0 | Q8: =ROUND(O8*G8,0) -> 0 | R8: =ROUND(Q8*H8,0) -> 0 | S8: =ROUND(Q8*I8,0) -> 0 | T8: =ROUND(S8*J8,0) -> 0 | U8: =S8-T8 -> 0 | V8: =O8*IFERROR(VLOOKUP(D8,'Inputs & Settings'!D6:E9,2,FALSE),0) -> 0 | W8: =T8*IFERROR(VLOOKUP(K8,'Inputs & Settings'!D6:E9,2,FALSE),0) -> 0 | X8: =O8*'Inputs & Settings'!B15 -> 0 | Y8: =R8*'Inputs & Settings'!B16 -> 0 | Z8: =S8*'Inputs & Settings'!B15 -> 0 | AA8: =P8*'Inputs & Settings'!B17 -> 0 | AB8: =IF(L8="Yes",ROUND((O8+S8)*M8,0),0) -> 0
A9: 8 | C9: ='Inputs & Settings'!B7 -> 2026-02 | D9: Marketing | E9: 0 | F9: 0 | G9: 0 | H9: 1 | I9: 1 | J9: 0 | K9: ='Inputs & Settings'!E13 -> Marketing | L9: ='Inputs & Settings'!B20 -> No | M9: 0 | O9: =ROUND(E9*(1-F9),0) -> 0 | P9: =E9-O9 -> 0 | Q9: =ROUND(O9*G9,0) -> 0 | R9: =ROUND(Q9*H9,0) -> 0 | S9: =ROUND(Q9*I9,0) -> 0 | T9: =ROUND(S9*J9,0) -> 0 | U9: =S9-T9 -> 0 | V9: =O9*IFERROR(VLOOKUP(D9,'Inputs & Settings'!D6:E9,2,FALSE),0) -> 0 | W9: =T9*IFERROR(VLOOKUP(K9,'Inputs & Settings'!D6:E9,2,FALSE),0) -> 0 | X9: =O9*'Inputs & Settings'!B15 -> 0 | Y9: =R9*'Inputs & Settings'!B16 -> 0 | Z9: =S9*'Inputs & Settings'!B15 -> 0 | AA9: =P9*'Inputs & Settings'!B17 -> 0 | AB9: =IF(L9="Yes",ROUND((O9+S9)*M9,0),0) -> 0
A10: 9 | C10: ='Inputs & Settings'!B7 -> 2026-02 | D10: Marketing | E10: 0 | F10: 0 | G10: 0 | H10: 1 | I10: 1 | J10: 0 | K10: ='Inputs & Settings'!E13 -> Marketing | L10: ='Inputs & Settings'!B20 -> No | M10: 0 | O10: =ROUND(E10*(1-F10),0) -> 0 | P10: =E10-O10 -> 0 | Q10: =ROUND(O10*G10,0) -> 0 | R10: =ROUND(Q10*H10,0) -> 0 | S10: =ROUND(Q10*I10,0) -> 0 | T10: =ROUND(S10*J10,0) -> 0 | U10: =S10-T10 -> 0 | V10: =O10*IFERROR(VLOOKUP(D10,'Inputs & Settings'!D6:E9,2,FALSE),0) -> 0 | W10: =T10*IFERROR(VLOOKUP(K10,'Inputs & Settings'!D6:E9,2,FALSE),0) -> 0 | X10: =O10*'Inputs & Settings'!B15 -> 0 | Y10: =R10*'Inputs & Settings'!B16 -> 0 | Z10: =S10*'Inputs & Settings'!B15 -> 0 | AA10: =P10*'Inputs & Settings'!B17 -> 0 | AB10: =IF(L10="Yes",ROUND((O10+S10)*M10,0),0) -> 0
A11: 10 | C11: ='Inputs & Settings'!B7 -> 2026-02 | D11: Marketing | E11: 0 | F11: 0 | G11: 0 | H11: 1 | I11: 1 | J11: 0 | K11: ='Inputs & Settings'!E13 -> Marketing | L11: ='Inputs & Settings'!B20 -> No | M11: 0 | O11: =ROUND(E11*(1-F11),0) -> 0 | P11: =E11-O11 -> 0 | Q11: =ROUND(O11*G11,0) -> 0 | R11: =ROUND(Q11*H11,0) -> 0 | S11: =ROUND(Q11*I11,0) -> 0 | T11: =ROUND(S11*J11,0) -> 0 | U11: =S11-T11 -> 0 | V11: =O11*IFERROR(VLOOKUP(D11,'Inputs & Settings'!D6:E9,2,FALSE),0) -> 0 | W11: =T11*IFERROR(VLOOKUP(K11,'Inputs & Settings'!D6:E9,2,FALSE),0) -> 0 | X11: =O11*'Inputs & Settings'!B15 -> 0 | Y11: =R11*'Inputs & Settings'!B16 -> 0 | Z11: =S11*'Inputs & Settings'!B15 -> 0 | AA11: =P11*'Inputs & Settings'!B17 -> 0 | AB11: =IF(L11="Yes",ROUND((O11+S11)*M11,0),0) -> 0
A12: 11 | C12: ='Inputs & Settings'!B7 -> 2026-02 | D12: Marketing | E12: 0 | F12: 0 | G12: 0 | H12: 1 | I12: 1 | J12: 0 | K12: ='Inputs & Settings'!E13 -> Marketing | L12: ='Inputs & Settings'!B20 -> No | M12: 0 | O12: =ROUND(E12*(1-F12),0) -> 0 | P12: =E12-O12 -> 0 | Q12: =ROUND(O12*G12,0) -> 0 | R12: =ROUND(Q12*H12,0) -> 0 | S12: =ROUND(Q12*I12,0) -> 0 | T12: =ROUND(S12*J12,0) -> 0 | U12: =S12-T12 -> 0 | V12: =O12*IFERROR(VLOOKUP(D12,'Inputs & Settings'!D6:E9,2,FALSE),0) -> 0 | W12: =T12*IFERROR(VLOOKUP(K12,'Inputs & Settings'!D6:E9,2,FALSE),0) -> 0 | X12: =O12*'Inputs & Settings'!B15 -> 0 | Y12: =R12*'Inputs & Settings'!B16 -> 0 | Z12: =S12*'Inputs & Settings'!B15 -> 0 | AA12: =P12*'Inputs & Settings'!B17 -> 0 | AB12: =IF(L12="Yes",ROUND((O12+S12)*M12,0),0) -> 0
A13: 12 | C13: ='Inputs & Settings'!B7 -> 2026-02 | D13: Marketing | E13: 0 | F13: 0 | G13: 0 | H13: 1 | I13: 1 | J13: 0 | K13: ='Inputs & Settings'!E13 -> Marketing | L13: ='Inputs & Settings'!B20 -> No | M13: 0 | O13: =ROUND(E13*(1-F13),0) -> 0 | P13: =E13-O13 -> 0 | Q13: =ROUND(O13*G13,0) -> 0 | R13: =ROUND(Q13*H13,0) -> 0 | S13: =ROUND(Q13*I13,0) -> 0 | T13: =ROUND(S13*J13,0) -> 0 | U13: =S13-T13 -> 0 | V13: =O13*IFERROR(VLOOKUP(D13,'Inputs & Settings'!D6:E9,2,FALSE),0) -> 0 | W13: =T13*IFERROR(VLOOKUP(K13,'Inputs & Settings'!D6:E9,2,FALSE),0) -> 0 | X13: =O13*'Inputs & Settings'!B15 -> 0 | Y13: =R13*'Inputs & Settings'!B16 -> 0 | Z13: =S13*'Inputs & Settings'!B15 -> 0 | AA13: =P13*'Inputs & Settings'!B17 -> 0 | AB13: =IF(L13="Yes",ROUND((O13+S13)*M13,0),0) -> 0
A14: 13 | C14: ='Inputs & Settings'!B7 -> 2026-02 | D14: Marketing | E14: 0 | F14: 0 | G14: 0 | H14: 1 | I14: 1 | J14: 0 | K14: ='Inputs & Settings'!E13 -> Marketing | L14: ='Inputs & Settings'!B20 -> No | M14: 0 | O14: =ROUND(E14*(1-F14),0) -> 0 | P14: =E14-O14 -> 0 | Q14: =ROUND(O14*G14,0) -> 0 | R14: =ROUND(Q14*H14,0) -> 0 | S14: =ROUND(Q14*I14,0) -> 0 | T14: =ROUND(S14*J14,0) -> 0 | U14: =S14-T14 -> 0 | V14: =O14*IFERROR(VLOOKUP(D14,'Inputs & Settings'!D6:E9,2,FALSE),0) -> 0 | W14: =T14*IFERROR(VLOOKUP(K14,'Inputs & Settings'!D6:E9,2,FALSE),0) -> 0 | X14: =O14*'Inputs & Settings'!B15 -> 0 | Y14: =R14*'Inputs & Settings'!B16 -> 0 | Z14: =S14*'Inputs & Settings'!B15 -> 0 | AA14: =P14*'Inputs & Settings'!B17 -> 0 | AB14: =IF(L14="Yes",ROUND((O14+S14)*M14,0),0) -> 0
A15: 14 | C15: ='Inputs & Settings'!B7 -> 2026-02 | D15: Marketing | E15: 0 | F15: 0 | G15: 0 | H15: 1 | I15: 1 | J15: 0 | K15: ='Inputs & Settings'!E13 -> Marketing | L15: ='Inputs & Settings'!B20 -> No | M15: 0 | O15: =ROUND(E15*(1-F15),0) -> 0 | P15: =E15-O15 -> 0 | Q15: =ROUND(O15*G15,0) -> 0 | R15: =ROUND(Q15*H15,0) -> 0 | S15: =ROUND(Q15*I15,0) -> 0 | T15: =ROUND(S15*J15,0) -> 0 | U15: =S15-T15 -> 0 | V15: =O15*IFERROR(VLOOKUP(D15,'Inputs & Settings'!D6:E9,2,FALSE),0) -> 0 | W15: =T15*IFERROR(VLOOKUP(K15,'Inputs & Settings'!D6:E9,2,FALSE),0) -> 0 | X15: =O15*'Inputs & Settings'!B15 -> 0 | Y15: =R15*'Inputs & Settings'!B16 -> 0 | Z15: =S15*'Inputs & Settings'!B15 -> 0 | AA15: =P15*'Inputs & Settings'!B17 -> 0 | AB15: =IF(L15="Yes",ROUND((O15+S15)*M15,0),0) -> 0
A16: 15 | C16: ='Inputs & Settings'!B7 -> 2026-02 | D16: Marketing | E16: 0 | F16: 0 | G16: 0 | H16: 1 | I16: 1 | J16: 0 | K16: ='Inputs & Settings'!E13 -> Marketing | L16: ='Inputs & Settings'!B20 -> No | M16: 0 | O16: =ROUND(E16*(1-F16),0) -> 0 | P16: =E16-O16 -> 0 | Q16: =ROUND(O16*G16,0) -> 0 | R16: =ROUND(Q16*H16,0) -> 0 | S16: =ROUND(Q16*I16,0) -> 0 | T16: =ROUND(S16*J16,0) -> 0 | U16: =S16-T16 -> 0 | V16: =O16*IFERROR(VLOOKUP(D16,'Inputs & Settings'!D6:E9,2,FALSE),0) -> 0 | W16: =T16*IFERROR(VLOOKUP(K16,'Inputs & Settings'!D6:E9,2,FALSE),0) -> 0 | X16: =O16*'Inputs & Settings'!B15 -> 0 | Y16: =R16*'Inputs & Settings'!B16 -> 0 | Z16: =S16*'Inputs & Settings'!B15 -> 0 | AA16: =P16*'Inputs & Settings'!B17 -> 0 | AB16: =IF(L16="Yes",ROUND((O16+S16)*M16,0),0) -> 0
A17: 16 | C17: ='Inputs & Settings'!B7 -> 2026-02 | D17: Marketing | E17: 0 | F17: 0 | G17: 0 | H17: 1 | I17: 1 | J17: 0 | K17: ='Inputs & Settings'!E13 -> Marketing | L17: ='Inputs & Settings'!B20 -> No | M17: 0 | O17: =ROUND(E17*(1-F17),0) -> 0 | P17: =E17-O17 -> 0 | Q17: =ROUND(O17*G17,0) -> 0 | R17: =ROUND(Q17*H17,0) -> 0 | S17: =ROUND(Q17*I17,0) -> 0 | T17: =ROUND(S17*J17,0) -> 0 | U17: =S17-T17 -> 0 | V17: =O17*IFERROR(VLOOKUP(D17,'Inputs & Settings'!D6:E9,2,FALSE),0) -> 0 | W17: =T17*IFERROR(VLOOKUP(K17,'Inputs & Settings'!D6:E9,2,FALSE),0) -> 0 | X17: =O17*'Inputs & Settings'!B15 -> 0 | Y17: =R17*'Inputs & Settings'!B16 -> 0 | Z17: =S17*'Inputs & Settings'!B15 -> 0 | AA17: =P17*'Inputs & Settings'!B17 -> 0 | AB17: =IF(L17="Yes",ROUND((O17+S17)*M17,0),0) -> 0
A18: 17 | C18: ='Inputs & Settings'!B7 -> 2026-02 | D18: Marketing | E18: 0 | F18: 0 | G18: 0 | H18: 1 | I18: 1 | J18: 0 | K18: ='Inputs & Settings'!E13 -> Marketing | L18: ='Inputs & Settings'!B20 -> No | M18: 0 | O18: =ROUND(E18*(1-F18),0) -> 0 | P18: =E18-O18 -> 0 | Q18: =ROUND(O18*G18,0) -> 0 | R18: =ROUND(Q18*H18,0) -> 0 | S18: =ROUND(Q18*I18,0) -> 0 | T18: =ROUND(S18*J18,0) -> 0 | U18: =S18-T18 -> 0 | V18: =O18*IFERROR(VLOOKUP(D18,'Inputs & Settings'!D6:E9,2,FALSE),0) -> 0 | W18: =T18*IFERROR(VLOOKUP(K18,'Inputs & Settings'!D6:E9,2,FALSE),0) -> 0 | X18: =O18*'Inputs & Settings'!B15 -> 0 | Y18: =R18*'Inputs & Settings'!B16 -> 0 | Z18: =S18*'Inputs & Settings'!B15 -> 0 | AA18: =P18*'Inputs & Settings'!B17 -> 0 | AB18: =IF(L18="Yes",ROUND((O18+S18)*M18,0),0) -> 0
A19: 18 | C19: ='Inputs & Settings'!B7 -> 2026-02 | D19: Marketing | E19: 0 | F19: 0 | G19: 0 | H19: 1 | I19: 1 | J19: 0 | K19: ='Inputs & Settings'!E13 -> Marketing | L19: ='Inputs & Settings'!B20 -> No | M19: 0 | O19: =ROUND(E19*(1-F19),0) -> 0 | P19: =E19-O19 -> 0 | Q19: =ROUND(O19*G19,0) -> 0 | R19: =ROUND(Q19*H19,0) -> 0 | S19: =ROUND(Q19*I19,0) -> 0 | T19: =ROUND(S19*J19,0) -> 0 | U19: =S19-T19 -> 0 | V19: =O19*IFERROR(VLOOKUP(D19,'Inputs & Settings'!D6:E9,2,FALSE),0) -> 0 | W19: =T19*IFERROR(VLOOKUP(K19,'Inputs & Settings'!D6:E9,2,FALSE),0) -> 0 | X19: =O19*'Inputs & Settings'!B15 -> 0 | Y19: =R19*'Inputs & Settings'!B16 -> 0 | Z19: =S19*'Inputs & Settings'!B15 -> 0 | AA19: =P19*'Inputs & Settings'!B17 -> 0 | AB19: =IF(L19="Yes",ROUND((O19+S19)*M19,0),0) -> 0
A20: 19 | C20: ='Inputs & Settings'!B7 -> 2026-02 | D20: Marketing | E20: 0 | F20: 0 | G20: 0 | H20: 1 | I20: 1 | J20: 0 | K20: ='Inputs & Settings'!E13 -> Marketing | L20: ='Inputs & Settings'!B20 -> No | M20: 0 | O20: =ROUND(E20*(1-F20),0) -> 0 | P20: =E20-O20 -> 0 | Q20: =ROUND(O20*G20,0) -> 0 | R20: =ROUND(Q20*H20,0) -> 0 | S20: =ROUND(Q20*I20,0) -> 0 | T20: =ROUND(S20*J20,0) -> 0 | U20: =S20-T20 -> 0 | V20: =O20*IFERROR(VLOOKUP(D20,'Inputs & Settings'!D6:E9,2,FALSE),0) -> 0 | W20: =T20*IFERROR(VLOOKUP(K20,'Inputs & Settings'!D6:E9,2,FALSE),0) -> 0 | X20: =O20*'Inputs & Settings'!B15 -> 0 | Y20: =R20*'Inputs & Settings'!B16 -> 0 | Z20: =S20*'Inputs & Settings'!B15 -> 0 | AA20: =P20*'Inputs & Settings'!B17 -> 0 | AB20: =IF(L20="Yes",ROUND((O20+S20)*M20,0),0) -> 0
A21: 20 | C21: ='Inputs & Settings'!B7 -> 2026-02 | D21: Marketing | E21: 0 | F21: 0 | G21: 0 | H21: 1 | I21: 1 | J21: 0 | K21: ='Inputs & Settings'!E13 -> Marketing | L21: ='Inputs & Settings'!B20 -> No | M21: 0 | O21: =ROUND(E21*(1-F21),0) -> 0 | P21: =E21-O21 -> 0 | Q21: =ROUND(O21*G21,0) -> 0 | R21: =ROUND(Q21*H21,0) -> 0 | S21: =ROUND(Q21*I21,0) -> 0 | T21: =ROUND(S21*J21,0) -> 0 | U21: =S21-T21 -> 0 | V21: =O21*IFERROR(VLOOKUP(D21,'Inputs & Settings'!D6:E9,2,FALSE),0) -> 0 | W21: =T21*IFERROR(VLOOKUP(K21,'Inputs & Settings'!D6:E9,2,FALSE),0) -> 0 | X21: =O21*'Inputs & Settings'!B15 -> 0 | Y21: =R21*'Inputs & Settings'!B16 -> 0 | Z21: =S21*'Inputs & Settings'!B15 -> 0 | AA21: =P21*'Inputs & Settings'!B17 -> 0 | AB21: =IF(L21="Yes",ROUND((O21+S21)*M21,0),0) -> 0

Sheet Monthly Summary
A1: Monthly Summary (all campaigns) | Y1: USD | Z1: 892.86 | AA1: 892.86
A2: Month | B2: Outbound Planned | C2: Outbound Delivered | D2: Outbound Failed | E2: Responders | F2: Inbound Msgs | G2: Reply Msgs | H2: Meta Cost (Outbound) | I2: Meta Cost (Reply Templates) | J2: Meta Cost (Total) | K2: Twilio Cost (Outbound) | L2: Twilio Cost (Inbound) | M2: Twilio Cost (Reply Outbound) | N2: Twilio Failed Fee | O2: Twilio Cost (Total) | P2: Engagement Msgs | Q2: Engagement Free Allowance | R2: Engagement Billable Msgs | S2: Engagement Cost | T2: Subtotal (Pre-Tax) | U2: Tax on Twilio | V2: Tax on Meta | W2: Total (With Tax) | X2: Manage | Y2: Total USD | Z2: Total USD | AA2: Total USD
A3: 2026-01 | B3: =SUMIF('Campaign Planner'!C:C,A3,'Campaign Planner'!E:E) -> 0 | C3: =SUMIF('Campaign Planner'!C:C,A3,'Campaign Planner'!O:O) -> 0 | D3: =SUMIF('Campaign Planner'!C:C,A3,'Campaign Planner'!P:P) -> 0 | E3: =SUMIF('Campaign Planner'!C:C,A3,'Campaign Planner'!Q:Q) -> 0 | F3: =SUMIF('Campaign Planner'!C:C,A3,'Campaign Planner'!R:R) -> 0 | G3: =SUMIF('Campaign Planner'!C:C,A3,'Campaign Planner'!S:S) -> 0 | H3: =SUMIF('Campaign Planner'!C:C,A3,'Campaign Planner'!V:V) -> 0 | I3: =SUMIF('Campaign Planner'!C:C,A3,'Campaign Planner'!W:W) -> 0 | J3: =H3+I3 -> 0 | K3: =SUMIF('Campaign Planner'!C:C,A3,'Campaign Planner'!X:X) -> 0 | L3: =SUMIF('Campaign Planner'!C:C,A3,'Campaign Planner'!Y:Y) -> 0 | M3: =SUMIF('Campaign Planner'!C:C,A3,'Campaign Planner'!Z:Z) -> 0 | N3: =SUMIF('Campaign Planner'!C:C,A3,'Campaign Planner'!AA:AA) -> 0 | O3: =K3+L3+M3+N3 -> 0 | P3: =SUMIF('Campaign Planner'!C:C,A3,'Campaign Planner'!AB:AB) -> 0 | Q3: ='Inputs & Settings'!B22 -> 1000 | R3: =MAX(0,P3-Q3) -> 0 | S3: =R3*'Inputs & Settings'!B21 -> 0 | T3: =J3+O3+S3 -> 0 | U3: =O3*'Inputs & Settings'!B10 -> 0 | V3: =J3*'Inputs & Settings'!B11 -> 0 | W3: =T3+U3+V3 -> 0 | X3: =W3*'Inputs & Settings'!E16 -> 0 | Y3: =W3+X3 -> 0 | Z3: =#REF!*Y3 -> #REF! | AA3: =Z3/B3 -> #REF!
A4: 2026-02 | B4: =SUMIF('Campaign Planner'!C:C,A4,'Campaign Planner'!E:E) -> 3000 | C4: =SUMIF('Campaign Planner'!C:C,A4,'Campaign Planner'!O:O) -> 2850 | D4: =SUMIF('Campaign Planner'!C:C,A4,'Campaign Planner'!P:P) -> 150 | E4: =SUMIF('Campaign Planner'!C:C,A4,'Campaign Planner'!Q:Q) -> 342 | F4: =SUMIF('Campaign Planner'!C:C,A4,'Campaign Planner'!R:R) -> 342 | G4: =SUMIF('Campaign Planner'!C:C,A4,'Campaign Planner'!S:S) -> 342 | H4: =SUMIF('Campaign Planner'!C:C,A4,'Campaign Planner'!V:V) -> 253.365 | I4: =SUMIF('Campaign Planner'!C:C,A4,'Campaign Planner'!W:W) -> 0 | J4: =H4+I4 -> 253.365 | K4: =SUMIF('Campaign Planner'!C:C,A4,'Campaign Planner'!X:X) -> 14.25 | L4: =SUMIF('Campaign Planner'!C:C,A4,'Campaign Planner'!Y:Y) -> 1.71 | M4: =SUMIF('Campaign Planner'!C:C,A4,'Campaign Planner'!Z:Z) -> 1.71 | N4: =SUMIF('Campaign Planner'!C:C,A4,'Campaign Planner'!AA:AA) -> 0.15 | O4: =K4+L4+M4+N4 -> 17.82 | P4: =SUMIF('Campaign Planner'!C:C,A4,'Campaign Planner'!AB:AB) -> 0 | Q4: ='Inputs & Settings'!B22 -> 1000 | R4: =MAX(0,P4-Q4) -> 0 | S4: =R4*'Inputs & Settings'!B21 -> 0 | T4: =J4+O4+S4 -> 271.185 | U4: =O4*'Inputs & Settings'!B10 -> 3.3858 | V4: =J4*'Inputs & Settings'!B11 -> 48.13935 | W4: =T4+U4+V4 -> 322.71015 | X4: =W4*'Inputs & Settings'!E16 -> 96.813045 | Y4: =W4+X4 -> 419.52319 | Z4: =Z1*Y4 -> 374575.48 | AA4: =Z4/B4 -> 124.85849
A5: 2026-03 | B5: =SUMIF('Campaign Planner'!C:C,A5,'Campaign Planner'!E:E) -> 0 | C5: =SUMIF('Campaign Planner'!C:C,A5,'Campaign Planner'!O:O) -> 0 | D5: =SUMIF('Campaign Planner'!C:C,A5,'Campaign Planner'!P:P) -> 0 | E5: =SUMIF('Campaign Planner'!C:C,A5,'Campaign Planner'!Q:Q) -> 0 | F5: =SUMIF('Campaign Planner'!C:C,A5,'Campaign Planner'!R:R) -> 0 | G5: =SUMIF('Campaign Planner'!C:C,A5,'Campaign Planner'!S:S) -> 0 | H5: =SUMIF('Campaign Planner'!C:C,A5,'Campaign Planner'!V:V) -> 0 | I5: =SUMIF('Campaign Planner'!C:C,A5,'Campaign Planner'!W:W) -> 0 | J5: =H5+I5 -> 0 | K5: =SUMIF('Campaign Planner'!C:C,A5,'Campaign Planner'!X:X) -> 0 | L5: =SUMIF('Campaign Planner'!C:C,A5,'Campaign Planner'!Y:Y) -> 0 | M5: =SUMIF('Campaign Planner'!C:C,A5,'Campaign Planner'!Z:Z) -> 0 | N5: =SUMIF('Campaign Planner'!C:C,A5,'Campaign Planner'!AA:AA) -> 0 | O5: =K5+L5+M5+N5 -> 0 | P5: =SUMIF('Campaign Planner'!C:C,A5,'Campaign Planner'!AB:AB) -> 0 | Q5: ='Inputs & Settings'!B22 -> 1000 | R5: =MAX(0,P5-Q5) -> 0 | S5: =R5*'Inputs & Settings'!B21 -> 0 | T5: =J5+O5+S5 -> 0 | U5: =O5*'Inputs & Settings'!B10 -> 0 | V5: =J5*'Inputs & Settings'!B11 -> 0 | W5: =T5+U5+V5 -> 0 | X5: =W5*'Inputs & Settings'!E16 -> 0 | Y5: =W5+X5 -> 0 | Z5: =Z2*Y5 -> #VALUE! | AA5: =Z5/B5 -> #VALUE!
A6: 2026-04 | B6: =SUMIF('Campaign Planner'!C:C,A6,'Campaign Planner'!E:E) -> 0 | C6: =SUMIF('Campaign Planner'!C:C,A6,'Campaign Planner'!O:O) -> 0 | D6: =SUMIF('Campaign Planner'!C:C,A6,'Campaign Planner'!P:P) -> 0 | E6: =SUMIF('Campaign Planner'!C:C,A6,'Campaign Planner'!Q:Q) -> 0 | F6: =SUMIF('Campaign Planner'!C:C,A6,'Campaign Planner'!R:R) -> 0 | G6: =SUMIF('Campaign Planner'!C:C,A6,'Campaign Planner'!S:S) -> 0 | H6: =SUMIF('Campaign Planner'!C:C,A6,'Campaign Planner'!V:V) -> 0 | I6: =SUMIF('Campaign Planner'!C:C,A6,'Campaign Planner'!W:W) -> 0 | J6: =H6+I6 -> 0 | K6: =SUMIF('Campaign Planner'!C:C,A6,'Campaign Planner'!X:X) -> 0 | L6: =SUMIF('Campaign Planner'!C:C,A6,'Campaign Planner'!Y:Y) -> 0 | M6: =SUMIF('Campaign Planner'!C:C,A6,'Campaign Planner'!Z:Z) -> 0 | N6: =SUMIF('Campaign Planner'!C:C,A6,'Campaign Planner'!AA:AA) -> 0 | O6: =K6+L6+M6+N6 -> 0 | P6: =SUMIF('Campaign Planner'!C:C,A6,'Campaign Planner'!AB:AB) -> 0 | Q6: ='Inputs & Settings'!B22 -> 1000 | R6: =MAX(0,P6-Q6) -> 0 | S6: =R6*'Inputs & Settings'!B21 -> 0 | T6: =J6+O6+S6 -> 0 | U6: =O6*'Inputs & Settings'!B10 -> 0 | V6: =J6*'Inputs & Settings'!B11 -> 0 | W6: =T6+U6+V6 -> 0 | X6: =W6*'Inputs & Settings'!E16 -> 0 | Y6: =W6+X6 -> 0 | AA6: =Z6/B6 -> #DIV/0!
A7: 2026-05 | B7: =SUMIF('Campaign Planner'!C:C,A7,'Campaign Planner'!E:E) -> 0 | C7: =SUMIF('Campaign Planner'!C:C,A7,'Campaign Planner'!O:O) -> 0 | D7: =SUMIF('Campaign Planner'!C:C,A7,'Campaign Planner'!P:P) -> 0 | E7: =SUMIF('Campaign Planner'!C:C,A7,'Campaign Planner'!Q:Q) -> 0 | F7: =SUMIF('Campaign Planner'!C:C,A7,'Campaign Planner'!R:R) -> 0 | G7: =SUMIF('Campaign Planner'!C:C,A7,'Campaign Planner'!S:S) -> 0 | H7: =SUMIF('Campaign Planner'!C:C,A7,'Campaign Planner'!V:V) -> 0 | I7: =SUMIF('Campaign Planner'!C:C,A7,'Campaign Planner'!W:W) -> 0 | J7: =H7+I7 -> 0 | K7: =SUMIF('Campaign Planner'!C:C,A7,'Campaign Planner'!X:X) -> 0 | L7: =SUMIF('Campaign Planner'!C:C,A7,'Campaign Planner'!Y:Y) -> 0 | M7: =SUMIF('Campaign Planner'!C:C,A7,'Campaign Planner'!Z:Z) -> 0 | N7: =SUMIF('Campaign Planner'!C:C,A7,'Campaign Planner'!AA:AA) -> 0 | O7: =K7+L7+M7+N7 -> 0 | P7: =SUMIF('Campaign Planner'!C:C,A7,'Campaign Planner'!AB:AB) -> 0 | Q7: ='Inputs & Settings'!B22 -> 1000 | R7: =MAX(0,P7-Q7) -> 0 | S7: =R7*'Inputs & Settings'!B21 -> 0 | T7: =J7+O7+S7 -> 0 | U7: =O7*'Inputs & Settings'!B10 -> 0 | V7: =J7*'Inputs & Settings'!B11 -> 0 | W7: =T7+U7+V7 -> 0 | X7: =W7*'Inputs & Settings'!E16 -> 0 | Y7: =W7+X7 -> 0 | AA7: =Z7/B7 -> #DIV/0!
A8: 2026-06 | B8: =SUMIF('Campaign Planner'!C:C,A8,'Campaign Planner'!E:E) -> 0 | C8: =SUMIF('Campaign Planner'!C:C,A8,'Campaign Planner'!O:O) -> 0 | D8: =SUMIF('Campaign Planner'!C:C,A8,'Campaign Planner'!P:P) -> 0 | E8: =SUMIF('Campaign Planner'!C:C,A8,'Campaign Planner'!Q:Q) -> 0 | F8: =SUMIF('Campaign Planner'!C:C,A8,'Campaign Planner'!R:R) -> 0 | G8: =SUMIF('Campaign Planner'!C:C,A8,'Campaign Planner'!S:S) -> 0 | H8: =SUMIF('Campaign Planner'!C:C,A8,'Campaign Planner'!V:V) -> 0 | I8: =SUMIF('Campaign Planner'!C:C,A8,'Campaign Planner'!W:W) -> 0 | J8: =H8+I8 -> 0 | K8: =SUMIF('Campaign Planner'!C:C,A8,'Campaign Planner'!X:X) -> 0 | L8: =SUMIF('Campaign Planner'!C:C,A8,'Campaign Planner'!Y:Y) -> 0 | M8: =SUMIF('Campaign Planner'!C:C,A8,'Campaign Planner'!Z:Z) -> 0 | N8: =SUMIF('Campaign Planner'!C:C,A8,'Campaign Planner'!AA:AA) -> 0 | O8: =K8+L8+M8+N8 -> 0 | P8: =SUMIF('Campaign Planner'!C:C,A8,'Campaign Planner'!AB:AB) -> 0 | Q8: ='Inputs & Settings'!B22 -> 1000 | R8: =MAX(0,P8-Q8) -> 0 | S8: =R8*'Inputs & Settings'!B21 -> 0 | T8: =J8+O8+S8 -> 0 | U8: =O8*'Inputs & Settings'!B10 -> 0 | V8: =J8*'Inputs & Settings'!B11 -> 0 | W8: =T8+U8+V8 -> 0 | X8: =W8*'Inputs & Settings'!E16 -> 0 | Y8: =W8+X8 -> 0 | AA8: =Z8/B8 -> #DIV/0!
A9: 2026-07 | B9: =SUMIF('Campaign Planner'!C:C,A9,'Campaign Planner'!E:E) -> 0 | C9: =SUMIF('Campaign Planner'!C:C,A9,'Campaign Planner'!O:O) -> 0 | D9: =SUMIF('Campaign Planner'!C:C,A9,'Campaign Planner'!P:P) -> 0 | E9: =SUMIF('Campaign Planner'!C:C,A9,'Campaign Planner'!Q:Q) -> 0 | F9: =SUMIF('Campaign Planner'!C:C,A9,'Campaign Planner'!R:R) -> 0 | G9: =SUMIF('Campaign Planner'!C:C,A9,'Campaign Planner'!S:S) -> 0 | H9: =SUMIF('Campaign Planner'!C:C,A9,'Campaign Planner'!V:V) -> 0 | I9: =SUMIF('Campaign Planner'!C:C,A9,'Campaign Planner'!W:W) -> 0 | J9: =H9+I9 -> 0 | K9: =SUMIF('Campaign Planner'!C:C,A9,'Campaign Planner'!X:X) -> 0 | L9: =SUMIF('Campaign Planner'!C:C,A9,'Campaign Planner'!Y:Y) -> 0 | M9: =SUMIF('Campaign Planner'!C:C,A9,'Campaign Planner'!Z:Z) -> 0 | N9: =SUMIF('Campaign Planner'!C:C,A9,'Campaign Planner'!AA:AA) -> 0 | O9: =K9+L9+M9+N9 -> 0 | P9: =SUMIF('Campaign Planner'!C:C,A9,'Campaign Planner'!AB:AB) -> 0 | Q9: ='Inputs & Settings'!B22 -> 1000 | R9: =MAX(0,P9-Q9) -> 0 | S9: =R9*'Inputs & Settings'!B21 -> 0 | T9: =J9+O9+S9 -> 0 | U9: =O9*'Inputs & Settings'!B10 -> 0 | V9: =J9*'Inputs & Settings'!B11 -> 0 | W9: =T9+U9+V9 -> 0 | X9: =W9*'Inputs & Settings'!E16 -> 0 | Y9: =W9+X9 -> 0 | AA9: =Z9/B9 -> #DIV/0!
A10: 2026-08 | B10: =SUMIF('Campaign Planner'!C:C,A10,'Campaign Planner'!E:E) -> 0 | C10: =SUMIF('Campaign Planner'!C:C,A10,'Campaign Planner'!O:O) -> 0 | D10: =SUMIF('Campaign Planner'!C:C,A10,'Campaign Planner'!P:P) -> 0 | E10: =SUMIF('Campaign Planner'!C:C,A10,'Campaign Planner'!Q:Q) -> 0 | F10: =SUMIF('Campaign Planner'!C:C,A10,'Campaign Planner'!R:R) -> 0 | G10: =SUMIF('Campaign Planner'!C:C,A10,'Campaign Planner'!S:S) -> 0 | H10: =SUMIF('Campaign Planner'!C:C,A10,'Campaign Planner'!V:V) -> 0 | I10: =SUMIF('Campaign Planner'!C:C,A10,'Campaign Planner'!W:W) -> 0 | J10: =H10+I10 -> 0 | K10: =SUMIF('Campaign Planner'!C:C,A10,'Campaign Planner'!X:X) -> 0 | L10: =SUMIF('Campaign Planner'!C:C,A10,'Campaign Planner'!Y:Y) -> 0 | M10: =SUMIF('Campaign Planner'!C:C,A10,'Campaign Planner'!Z:Z) -> 0 | N10: =SUMIF('Campaign Planner'!C:C,A10,'Campaign Planner'!AA:AA) -> 0 | O10: =K10+L10+M10+N10 -> 0 | P10: =SUMIF('Campaign Planner'!C:C,A10,'Campaign Planner'!AB:AB) -> 0 | Q10: ='Inputs & Settings'!B22 -> 1000 | R10: =MAX(0,P10-Q10) -> 0 | S10: =R10*'Inputs & Settings'!B21 -> 0 | T10: =J10+O10+S10 -> 0 | U10: =O10*'Inputs & Settings'!B10 -> 0 | V10: =J10*'Inputs & Settings'!B11 -> 0 | W10: =T10+U10+V10 -> 0 | X10: =W10*'Inputs & Settings'!E16 -> 0 | Y10: =W10+X10 -> 0 | AA10: =Z10/B10 -> #DIV/0!
A11: 2026-09 | B11: =SUMIF('Campaign Planner'!C:C,A11,'Campaign Planner'!E:E) -> 0 | C11: =SUMIF('Campaign Planner'!C:C,A11,'Campaign Planner'!O:O) -> 0 | D11: =SUMIF('Campaign Planner'!C:C,A11,'Campaign Planner'!P:P) -> 0 | E11: =SUMIF('Campaign Planner'!C:C,A11,'Campaign Planner'!Q:Q) -> 0 | F11: =SUMIF('Campaign Planner'!C:C,A11,'Campaign Planner'!R:R) -> 0 | G11: =SUMIF('Campaign Planner'!C:C,A11,'Campaign Planner'!S:S) -> 0 | H11: =SUMIF('Campaign Planner'!C:C,A11,'Campaign Planner'!V:V) -> 0 | I11: =SUMIF('Campaign Planner'!C:C,A11,'Campaign Planner'!W:W) -> 0 | J11: =H11+I11 -> 0 | K11: =SUMIF('Campaign Planner'!C:C,A11,'Campaign Planner'!X:X) -> 0 | L11: =SUMIF('Campaign Planner'!C:C,A11,'Campaign Planner'!Y:Y) -> 0 | M11: =SUMIF('Campaign Planner'!C:C,A11,'Campaign Planner'!Z:Z) -> 0 | N11: =SUMIF('Campaign Planner'!C:C,A11,'Campaign Planner'!AA:AA) -> 0 | O11: =K11+L11+M11+N11 -> 0 | P11: =SUMIF('Campaign Planner'!C:C,A11,'Campaign Planner'!AB:AB) -> 0 | Q11: ='Inputs & Settings'!B22 -> 1000 | R11: =MAX(0,P11-Q11) -> 0 | S11: =R11*'Inputs & Settings'!B21 -> 0 | T11: =J11+O11+S11 -> 0 | U11: =O11*'Inputs & Settings'!B10 -> 0 | V11: =J11*'Inputs & Settings'!B11 -> 0 | W11: =T11+U11+V11 -> 0 | X11: =W11*'Inputs & Settings'!E16 -> 0 | Y11: =W11+X11 -> 0 | AA11: =Z11/B11 -> #DIV/0!
A12: 2026-10 | B12: =SUMIF('Campaign Planner'!C:C,A12,'Campaign Planner'!E:E) -> 0 | C12: =SUMIF('Campaign Planner'!C:C,A12,'Campaign Planner'!O:O) -> 0 | D12: =SUMIF('Campaign Planner'!C:C,A12,'Campaign Planner'!P:P) -> 0 | E12: =SUMIF('Campaign Planner'!C:C,A12,'Campaign Planner'!Q:Q) -> 0 | F12: =SUMIF('Campaign Planner'!C:C,A12,'Campaign Planner'!R:R) -> 0 | G12: =SUMIF('Campaign Planner'!C:C,A12,'Campaign Planner'!S:S) -> 0 | H12: =SUMIF('Campaign Planner'!C:C,A12,'Campaign Planner'!V:V) -> 0 | I12: =SUMIF('Campaign Planner'!C:C,A12,'Campaign Planner'!W:W) -> 0 | J12: =H12+I12 -> 0 | K12: =SUMIF('Campaign Planner'!C:C,A12,'Campaign Planner'!X:X) -> 0 | L12: =SUMIF('Campaign Planner'!C:C,A12,'Campaign Planner'!Y:Y) -> 0 | M12: =SUMIF('Campaign Planner'!C:C,A12,'Campaign Planner'!Z:Z) -> 0 | N12: =SUMIF('Campaign Planner'!C:C,A12,'Campaign Planner'!AA:AA) -> 0 | O12: =K12+L12+M12+N12 -> 0 | P12: =SUMIF('Campaign Planner'!C:C,A12,'Campaign Planner'!AB:AB) -> 0 | Q12: ='Inputs & Settings'!B22 -> 1000 | R12: =MAX(0,P12-Q12) -> 0 | S12: =R12*'Inputs & Settings'!B21 -> 0 | T12: =J12+O12+S12 -> 0 | U12: =O12*'Inputs & Settings'!B10 -> 0 | V12: =J12*'Inputs & Settings'!B11 -> 0 | W12: =T12+U12+V12 -> 0 | X12: =W12*'Inputs & Settings'!E16 -> 0 | Y12: =W12+X12 -> 0 | AA12: =Z12/B12 -> #DIV/0!
A13: 2026-11 | B13: =SUMIF('Campaign Planner'!C:C,A13,'Campaign Planner'!E:E) -> 0 | C13: =SUMIF('Campaign Planner'!C:C,A13,'Campaign Planner'!O:O) -> 0 | D13: =SUMIF('Campaign Planner'!C:C,A13,'Campaign Planner'!P:P) -> 0 | E13: =SUMIF('Campaign Planner'!C:C,A13,'Campaign Planner'!Q:Q) -> 0 | F13: =SUMIF('Campaign Planner'!C:C,A13,'Campaign Planner'!R:R) -> 0 | G13: =SUMIF('Campaign Planner'!C:C,A13,'Campaign Planner'!S:S) -> 0 | H13: =SUMIF('Campaign Planner'!C:C,A13,'Campaign Planner'!V:V) -> 0 | I13: =SUMIF('Campaign Planner'!C:C,A13,'Campaign Planner'!W:W) -> 0 | J13: =H13+I13 -> 0 | K13: =SUMIF('Campaign Planner'!C:C,A13,'Campaign Planner'!X:X) -> 0 | L13: =SUMIF('Campaign Planner'!C:C,A13,'Campaign Planner'!Y:Y) -> 0 | M13: =SUMIF('Campaign Planner'!C:C,A13,'Campaign Planner'!Z:Z) -> 0 | N13: =SUMIF('Campaign Planner'!C:C,A13,'Campaign Planner'!AA:AA) -> 0 | O13: =K13+L13+M13+N13 -> 0 | P13: =SUMIF('Campaign Planner'!C:C,A13,'Campaign Planner'!AB:AB) -> 0 | Q13: ='Inputs & Settings'!B22 -> 1000 | R13: =MAX(0,P13-Q13) -> 0 | S13: =R13*'Inputs & Settings'!B21 -> 0 | T13: =J13+O13+S13 -> 0 | U13: =O13*'Inputs & Settings'!B10 -> 0 | V13: =J13*'Inputs & Settings'!B11 -> 0 | W13: =T13+U13+V13 -> 0 | X13: =W13*'Inputs & Settings'!E16 -> 0 | Y13: =W13+X13 -> 0 | AA13: =Z13/B13 -> #DIV/0!
A14: 2026-12 | B14: =SUMIF('Campaign Planner'!C:C,A14,'Campaign Planner'!E:E) -> 0 | C14: =SUMIF('Campaign Planner'!C:C,A14,'Campaign Planner'!O:O) -> 0 | D14: =SUMIF('Campaign Planner'!C:C,A14,'Campaign Planner'!P:P) -> 0 | E14: =SUMIF('Campaign Planner'!C:C,A14,'Campaign Planner'!Q:Q) -> 0 | F14: =SUMIF('Campaign Planner'!C:C,A14,'Campaign Planner'!R:R) -> 0 | G14: =SUMIF('Campaign Planner'!C:C,A14,'Campaign Planner'!S:S) -> 0 | H14: =SUMIF('Campaign Planner'!C:C,A14,'Campaign Planner'!V:V) -> 0 | I14: =SUMIF('Campaign Planner'!C:C,A14,'Campaign Planner'!W:W) -> 0 | J14: =H14+I14 -> 0 | K14: =SUMIF('Campaign Planner'!C:C,A14,'Campaign Planner'!X:X) -> 0 | L14: =SUMIF('Campaign Planner'!C:C,A14,'Campaign Planner'!Y:Y) -> 0 | M14: =SUMIF('Campaign Planner'!C:C,A14,'Campaign Planner'!Z:Z) -> 0 | N14: =SUMIF('Campaign Planner'!C:C,A14,'Campaign Planner'!AA:AA) -> 0 | O14: =K14+L14+M14+N14 -> 0 | P14: =SUMIF('Campaign Planner'!C:C,A14,'Campaign Planner'!AB:AB) -> 0 | Q14: ='Inputs & Settings'!B22 -> 1000 | R14: =MAX(0,P14-Q14) -> 0 | S14: =R14*'Inputs & Settings'!B21 -> 0 | T14: =J14+O14+S14 -> 0 | U14: =O14*'Inputs & Settings'!B10 -> 0 | V14: =J14*'Inputs & Settings'!B11 -> 0 | W14: =T14+U14+V14 -> 0 | X14: =W14*'Inputs & Settings'!E16 -> 0 | Y14: =W14+X14 -> 0 | AA14: =Z14/B14 -> #DIV/0!
A16: Notes | B16: Fill campaigns in 'Campaign Planner'. Adjust rates & taxes in 'Inputs & Settings'.

Sheet Quick Scenario
A1: Quick Scenario: 500 WhatsApp (Chile)
A3: Outbound Category | B3: Marketing | D3: Delivered | E3: =ROUND(B4*(1-B5),0) -> 500
A4: Outbound Planned | B4: 500 | D4: Meta cost outbound | E4: =E3*IFERROR(VLOOKUP(B3,'Inputs & Settings'!D6:E9,2,FALSE),0) -> 44.45
A5: Failure Rate | B5: 0 | D5: Twilio cost outbound | E5: =E3*'Inputs & Settings'!B15 -> 2.5
A6: Response Rate | B6: 0.2 | D6: Responders | E6: =ROUND(E3*B6,0) -> 100
A7: Avg inbound msgs / responder | B7: 1 | D7: Inbound msgs | E7: =ROUND(E6*B7,0) -> 100
A8: Avg reply msgs / responder | B8: 1 | D8: Reply msgs | E8: =ROUND(E6*B8,0) -> 100
A9: Reply template % | B9: 0 | D9: Twilio inbound cost | E9: =E7*'Inputs & Settings'!B16 -> 0.5
D10: Twilio reply cost | E10: =E8*'Inputs & Settings'!B15 -> 0.5
D11: Subtotal (no tax) | E11: =E4+E5+E9+E10 -> 47.95
